{
  "pools": [
    {
      "rolls": 1,
      "entries": [
        {
          "type": "minecraft:item",
          "name": "minecraft:ink_sac",
          "functions": [
            {
              "function": "minecraft:set_components",
              "components": {
                "minecraft:custom_data": {
                  "looting": {
                    "tier": 1,
                    "price": 20,
                    "name": {
                      "text": "墨袋",
                      "color": "white"
                    },
                    "lore": [
                      "実はおいしいだけではなく体に良い"
                    ]
                  }
                },
                "minecraft:custom_name": {
                  "text": "?????",
                  "italic": false
                },
                "minecraft:item_name": "",
                "minecraft:rarity": "common"
              }
            }
          ]
        }
      ]
    }
  ]
}